{
  "data": [
    [
      [
        1,
        null,
        0,
        0.0
      ],
      [
        0.16410000000000002,
        68.17860245704651,
        {
          "__enum__": "StatusType.SUCCESS"
        },
        1638628628.221532,
        1638628696.4612887,
        {}
      ]
    ],
    [
      [
        2,
        null,
        0,
        0.0
      ],
      [
        0.12860000000000005,
        74.93878316879272,
        {
          "__enum__": "StatusType.SUCCESS"
        },
        1638628696.531762,
        1638628771.5158522,
        {}
      ]
    ],
    [
      [
        3,
        null,
        0,
        0.0
      ],
      [
        0.1985,
        68.47835373878479,
        {
          "__enum__": "StatusType.SUCCESS"
        },
        1638628771.559129,
        1638628840.1245227,
        {}
      ]
    ],
    [
      [
        4,
        null,
        0,
        0.0
      ],
      [
        0.14549999999999996,
        97.8797254562378,
        {
          "__enum__": "StatusType.SUCCESS"
        },
        1638628840.1271014,
        1638628938.0487795,
        {}
      ]
    ],
    [
      [
        5,
        null,
        0,
        0.0
      ],
      [
        0.19169999999999998,
        51.5433132648468,
        {
          "__enum__": "StatusType.SUCCESS"
        },
        1638628938.051135,
        1638628989.6605384,
        {}
      ]
    ],
    [
      [
        6,
        null,
        0,
        0.0
      ],
      [
        0.19840000000000002,
        56.40062761306763,
        {
          "__enum__": "StatusType.SUCCESS"
        },
        1638628989.6627443,
        1638629046.1233597,
        {}
      ]
    ],
    [
      [
        7,
        null,
        0,
        0.0
      ],
      [
        0.17379999999999995,
        54.760985136032104,
        {
          "__enum__": "StatusType.SUCCESS"
        },
        1638629046.1259766,
        1638629100.9526074,
        {}
      ]
    ],
    [
      [
        8,
        null,
        0,
        0.0
      ],
      [
        0.1946,
        91.78642725944519,
        {
          "__enum__": "StatusType.SUCCESS"
        },
        1638629100.9552135,
        1638629192.8379931,
        {}
      ]
    ],
    [
      [
        9,
        null,
        0,
        0.0
      ],
      [
        0.15169999999999995,
        48.02339959144592,
        {
          "__enum__": "StatusType.SUCCESS"
        },
        1638629192.8406963,
        1638629240.9218893,
        {}
      ]
    ],
    [
      [
        10,
        null,
        0,
        0.0
      ],
      [
        0.18469999999999998,
        48.95339608192444,
        {
          "__enum__": "StatusType.SUCCESS"
        },
        1638629240.9242675,
        1638629289.9173582,
        {}
      ]
    ],
    [
      [
        11,
        null,
        0,
        0.0
      ],
      [
        0.15710000000000002,
        101.60800862312317,
        {
          "__enum__": "StatusType.SUCCESS"
        },
        1638629289.9198618,
        1638629391.627271,
        {}
      ]
    ],
    [
      [
        12,
        null,
        0,
        0.0
      ],
      [
        0.1119,
        79.60459542274475,
        {
          "__enum__": "StatusType.SUCCESS"
        },
        1638629391.6291516,
        1638629471.2908497,
        {}
      ]
    ],
    [
      [
        13,
        null,
        0,
        0.0
      ],
      [
        0.12260000000000004,
        72.39100480079651,
        {
          "__enum__": "StatusType.SUCCESS"
        },
        1638629471.3826811,
        1638629543.8417404,
        {}
      ]
    ],
    [
      [
        14,
        null,
        0,
        0.0
      ],
      [
        0.14080000000000004,
        42.67542386054993,
        {
          "__enum__": "StatusType.SUCCESS"
        },
        1638629543.8442414,
        1638629586.5703707,
        {}
      ]
    ],
    [
      [
        15,
        null,
        0,
        0.0
      ],
      [
        0.14080000000000004,
        63.58431816101074,
        {
          "__enum__": "StatusType.SUCCESS"
        },
        1638629586.5724947,
        1638629650.1976476,
        {}
      ]
    ],
    [
      [
        16,
        null,
        0,
        0.0
      ],
      [
        0.14700000000000002,
        88.95434188842773,
        {
          "__enum__": "StatusType.SUCCESS"
        },
        1638629650.1998498,
        1638629739.2363112,
        {}
      ]
    ],
    [
      [
        17,
        null,
        0,
        0.0
      ],
      [
        0.1291,
        67.91005516052246,
        {
          "__enum__": "StatusType.SUCCESS"
        },
        1638629739.2383158,
        1638629807.2111592,
        {}
      ]
    ],
    [
      [
        18,
        null,
        0,
        0.0
      ],
      [
        0.13060000000000005,
        81.1233742237091,
        {
          "__enum__": "StatusType.SUCCESS"
        },
        1638629807.2136948,
        1638629888.3785005,
        {}
      ]
    ],
    [
      [
        19,
        null,
        0,
        0.0
      ],
      [
        0.15980000000000005,
        93.44218420982361,
        {
          "__enum__": "StatusType.SUCCESS"
        },
        1638629888.3810558,
        1638629981.8629818,
        {}
      ]
    ],
    [
      [
        20,
        null,
        0,
        0.0
      ],
      [
        0.1754,
        76.09842157363892,
        {
          "__enum__": "StatusType.SUCCESS"
        },
        1638629981.8655343,
        1638630058.060631,
        {}
      ]
    ],
    [
      [
        21,
        null,
        0,
        0.0
      ],
      [
        0.16710000000000003,
        58.74186873435974,
        {
          "__enum__": "StatusType.SUCCESS"
        },
        1638630058.0634313,
        1638630116.8762152,
        {}
      ]
    ],
    [
      [
        22,
        null,
        0,
        0.0
      ],
      [
        0.18420000000000003,
        50.12205195426941,
        {
          "__enum__": "StatusType.SUCCESS"
        },
        1638630116.8784914,
        1638630167.0662205,
        {}
      ]
    ],
    [
      [
        23,
        null,
        0,
        0.0
      ],
      [
        0.14139999999999997,
        82.90365505218506,
        {
          "__enum__": "StatusType.SUCCESS"
        },
        1638630167.0688064,
        1638630250.0134633,
        {}
      ]
    ],
    [
      [
        24,
        null,
        0,
        0.0
      ],
      [
        0.14370000000000005,
        90.33699488639832,
        {
          "__enum__": "StatusType.SUCCESS"
        },
        1638630250.0155642,
        1638630340.4416327,
        {}
      ]
    ],
    [
      [
        25,
        null,
        0,
        0.0
      ],
      [
        0.19099999999999995,
        48.83606696128845,
        {
          "__enum__": "StatusType.SUCCESS"
        },
        1638630340.4436316,
        1638630389.3319948,
        {}
      ]
    ],
    [
      [
        26,
        null,
        0,
        0.0
      ],
      [
        0.26480000000000004,
        69.21812653541565,
        {
          "__enum__": "StatusType.SUCCESS"
        },
        1638630389.3356454,
        1638630458.6147842,
        {}
      ]
    ],
    [
      [
        27,
        null,
        0,
        0.0
      ],
      [
        0.13570000000000004,
        43.933746576309204,
        {
          "__enum__": "StatusType.SUCCESS"
        },
        1638630459.6648927,
        1638630503.6606784,
        {}
      ]
    ],
    [
      [
        28,
        null,
        0,
        0.0
      ],
      [
        0.1926,
        67.21024966239929,
        {
          "__enum__": "StatusType.SUCCESS"
        },
        1638630505.0420895,
        1638630572.3143687,
        {}
      ]
    ],
    [
      [
        29,
        null,
        0,
        0.0
      ],
      [
        0.13470000000000004,
        73.04305052757263,
        {
          "__enum__": "StatusType.SUCCESS"
        },
        1638630573.3661687,
        1638630646.4563105,
        {}
      ]
    ],
    [
      [
        30,
        null,
        0,
        0.0
      ],
      [
        0.13639999999999997,
        61.72541904449463,
        {
          "__enum__": "StatusType.SUCCESS"
        },
        1638630646.4827278,
        1638630708.2499087,
        {}
      ]
    ],
    [
      [
        31,
        null,
        0,
        0.0
      ],
      [
        0.11980000000000002,
        95.8271415233612,
        {
          "__enum__": "StatusType.SUCCESS"
        },
        1638630708.2714982,
        1638630804.15904,
        {}
      ]
    ],
    [
      [
        32,
        null,
        0,
        0.0
      ],
      [
        0.1441,
        62.301324129104614,
        {
          "__enum__": "StatusType.SUCCESS"
        },
        1638630805.5403807,
        1638630867.8796833,
        {}
      ]
    ],
    [
      [
        33,
        null,
        0,
        0.0
      ],
      [
        0.1632,
        59.17087364196777,
        {
          "__enum__": "StatusType.SUCCESS"
        },
        1638630869.193261,
        1638630928.4054232,
        {}
      ]
    ],
    [
      [
        34,
        null,
        0,
        0.0
      ],
      [
        0.12649999999999995,
        86.29069423675537,
        {
          "__enum__": "StatusType.SUCCESS"
        },
        1638630929.4830248,
        1638631015.8226888,
        {}
      ]
    ],
    [
      [
        35,
        null,
        0,
        0.0
      ],
      [
        0.14629999999999999,
        71.83042120933533,
        {
          "__enum__": "StatusType.SUCCESS"
        },
        1638631017.159667,
        1638631089.0334044,
        {}
      ]
    ],
    [
      [
        36,
        null,
        0,
        0.0
      ],
      [
        0.12929999999999997,
        97.37624216079712,
        {
          "__enum__": "StatusType.SUCCESS"
        },
        1638631090.0592766,
        1638631187.4744246,
        {}
      ]
    ],
    [
      [
        37,
        null,
        0,
        0.0
      ],
      [
        0.15739999999999998,
        63.75849676132202,
        {
          "__enum__": "StatusType.SUCCESS"
        },
        1638631188.873374,
        1638631252.6842456,
        {}
      ]
    ],
    [
      [
        38,
        null,
        0,
        0.0
      ],
      [
        0.17020000000000002,
        73.56530022621155,
        {
          "__enum__": "StatusType.SUCCESS"
        },
        1638631254.087002,
        1638631327.6917908,
        {}
      ]
    ],
    [
      [
        39,
        null,
        0,
        0.0
      ],
      [
        0.1804,
        62.914353370666504,
        {
          "__enum__": "StatusType.SUCCESS"
        },
        1638631328.7059093,
        1638631391.6827435,
        {}
      ]
    ],
    [
      [
        40,
        null,
        0,
        0.0
      ],
      [
        0.17069999999999996,
        48.30853605270386,
        {
          "__enum__": "StatusType.SUCCESS"
        },
        1638631393.0694163,
        1638631441.4188619,
        {}
      ]
    ],
    [
      [
        41,
        null,
        0,
        0.0
      ],
      [
        0.17830000000000001,
        60.03651309013367,
        {
          "__enum__": "StatusType.SUCCESS"
        },
        1638631442.7822242,
        1638631502.8806465,
        {}
      ]
    ],
    [
      [
        42,
        null,
        0,
        0.0
      ],
      [
        0.15459999999999996,
        58.651432514190674,
        {
          "__enum__": "StatusType.SUCCESS"
        },
        1638631503.8459384,
        1638631562.5741324,
        {}
      ]
    ],
    [
      [
        43,
        null,
        0,
        0.0
      ],
      [
        0.12960000000000005,
        79.48182559013367,
        {
          "__enum__": "StatusType.SUCCESS"
        },
        1638631562.606281,
        1638631642.129391,
        {}
      ]
    ],
    [
      [
        44,
        null,
        0,
        0.0
      ],
      [
        0.13029999999999997,
        65.54479265213013,
        {
          "__enum__": "StatusType.SUCCESS"
        },
        1638631643.5568073,
        1638631709.1598299,
        {}
      ]
    ],
    [
      [
        45,
        null,
        0,
        0.0
      ],
      [
        0.15649999999999997,
        46.247108936309814,
        {
          "__enum__": "StatusType.SUCCESS"
        },
        1638631709.1924803,
        1638631755.4858646,
        {}
      ]
    ],
    [
      [
        46,
        null,
        0,
        0.0
      ],
      [
        0.13849999999999996,
        79.6297197341919,
        {
          "__enum__": "StatusType.SUCCESS"
        },
        1638631756.508668,
        1638631836.1854088,
        {}
      ]
    ],
    [
      [
        47,
        null,
        0,
        0.0
      ],
      [
        0.13190000000000002,
        66.37222266197205,
        {
          "__enum__": "StatusType.SUCCESS"
        },
        1638631837.65001,
        1638631904.0983107,
        {}
      ]
    ],
    [
      [
        48,
        null,
        0,
        0.0
      ],
      [
        0.1381,
        66.40519332885742,
        {
          "__enum__": "StatusType.SUCCESS"
        },
        1638631905.4303553,
        1638631971.874308,
        {}
      ]
    ],
    [
      [
        49,
        null,
        0,
        0.0
      ],
      [
        0.1703,
        46.87151622772217,
        {
          "__enum__": "StatusType.SUCCESS"
        },
        1638631971.9076521,
        1638632018.8349695,
        {}
      ]
    ],
    [
      [
        50,
        null,
        0,
        0.0
      ],
      [
        0.14629999999999999,
        69.55345940589905,
        {
          "__enum__": "StatusType.SUCCESS"
        },
        1638632019.841813,
        1638632089.4336455,
        {}
      ]
    ],
    [
      [
        51,
        null,
        0,
        0.0
      ],
      [
        0.17559999999999998,
        100.3132553100586,
        {
          "__enum__": "StatusType.SUCCESS"
        },
        1638632090.8018925,
        1638632191.162321,
        {}
      ]
    ],
    [
      [
        52,
        null,
        0,
        0.0
      ],
      [
        0.1442,
        91.33655524253845,
        {
          "__enum__": "StatusType.SUCCESS"
        },
        1638632191.1977968,
        1638632282.5866427,
        {}
      ]
    ],
    [
      [
        53,
        null,
        0,
        0.0
      ],
      [
        0.12980000000000003,
        68.49756908416748,
        {
          "__enum__": "StatusType.SUCCESS"
        },
        1638632283.9412322,
        1638632352.5007486,
        {}
      ]
    ],
    [
      [
        54,
        null,
        0,
        0.0
      ],
      [
        0.14249999999999996,
        73.35631966590881,
        {
          "__enum__": "StatusType.SUCCESS"
        },
        1638632353.5582643,
        1638632426.9612346,
        {}
      ]
    ],
    [
      [
        55,
        null,
        0,
        0.0
      ],
      [
        0.12,
        87.20129251480103,
        {
          "__enum__": "StatusType.SUCCESS"
        },
        1638632428.2969234,
        1638632515.5616958,
        {}
      ]
    ],
    [
      [
        56,
        null,
        0,
        0.0
      ],
      [
        0.13890000000000002,
        100.14559626579285,
        {
          "__enum__": "StatusType.SUCCESS"
        },
        1638632515.6013172,
        1638632615.811292,
        {}
      ]
    ],
    [
      [
        57,
        null,
        0,
        0.0
      ],
      [
        0.11639999999999995,
        34.976296186447144,
        {
          "__enum__": "StatusType.SUCCESS"
        },
        1638632617.2210267,
        1638632652.255224,
        {}
      ]
    ],
    [
      [
        58,
        null,
        0,
        0.0
      ],
      [
        0.12229999999999996,
        73.16517925262451,
        {
          "__enum__": "StatusType.SUCCESS"
        },
        1638632653.242671,
        1638632726.449623,
        {}
      ]
    ],
    [
      [
        59,
        null,
        0,
        0.0
      ],
      [
        0.21419999999999995,
        57.18703651428223,
        {
          "__enum__": "StatusType.SUCCESS"
        },
        1638632727.7934341,
        1638632785.031403,
        {}
      ]
    ],
    [
      [
        60,
        null,
        0,
        0.0
      ],
      [
        0.15739999999999998,
        60.92309331893921,
        {
          "__enum__": "StatusType.SUCCESS"
        },
        1638632785.070838,
        1638632846.0692065,
        {}
      ]
    ],
    [
      [
        61,
        null,
        0,
        0.0
      ],
      [
        0.12860000000000005,
        77.95868563652039,
        {
          "__enum__": "StatusType.SUCCESS"
        },
        1638632846.102373,
        1638632924.1242607,
        {}
      ]
    ],
    [
      [
        62,
        null,
        0,
        0.0
      ],
      [
        0.12880000000000003,
        73.49192237854004,
        {
          "__enum__": "StatusType.SUCCESS"
        },
        1638632925.534616,
        1638632999.0874636,
        {}
      ]
    ],
    [
      [
        63,
        null,
        0,
        0.0
      ],
      [
        0.1493,
        47.54993009567261,
        {
          "__enum__": "StatusType.SUCCESS"
        },
        1638632999.1269894,
        1638633046.7576983,
        {}
      ]
    ],
    [
      [
        64,
        null,
        0,
        0.0
      ],
      [
        0.15469999999999995,
        78.87037920951843,
        {
          "__enum__": "StatusType.SUCCESS"
        },
        1638633047.9069154,
        1638633126.8174534,
        {}
      ]
    ],
    [
      [
        65,
        null,
        0,
        0.0
      ],
      [
        0.12839999999999996,
        57.853782653808594,
        {
          "__enum__": "StatusType.SUCCESS"
        },
        1638633128.2248507,
        1638633186.1167178,
        {}
      ]
    ],
    [
      [
        66,
        null,
        0,
        0.0
      ],
      [
        0.20299999999999996,
        58.11724519729614,
        {
          "__enum__": "StatusType.SUCCESS"
        },
        1638633187.0451536,
        1638633245.2222464,
        {}
      ]
    ],
    [
      [
        67,
        null,
        0,
        0.0
      ],
      [
        0.129,
        59.073275327682495,
        {
          "__enum__": "StatusType.SUCCESS"
        },
        1638633245.2641416,
        1638633304.403312,
        {}
      ]
    ],
    [
      [
        68,
        null,
        0,
        0.0
      ],
      [
        0.16359999999999997,
        53.17034149169922,
        {
          "__enum__": "StatusType.SUCCESS"
        },
        1638633305.802042,
        1638633359.035419,
        {}
      ]
    ],
    [
      [
        69,
        null,
        0,
        0.0
      ],
      [
        0.13749999999999996,
        59.66677284240723,
        {
          "__enum__": "StatusType.SUCCESS"
        },
        1638633360.0912373,
        1638633419.821115,
        {}
      ]
    ],
    [
      [
        70,
        null,
        0,
        0.0
      ],
      [
        0.13560000000000005,
        56.852744579315186,
        {
          "__enum__": "StatusType.SUCCESS"
        },
        1638633421.1826017,
        1638633478.0735943,
        {}
      ]
    ],
    [
      [
        71,
        null,
        0,
        0.0
      ],
      [
        0.15049999999999997,
        63.50272536277771,
        {
          "__enum__": "StatusType.SUCCESS"
        },
        1638633479.5060127,
        1638633543.0639975,
        {}
      ]
    ],
    [
      [
        72,
        null,
        0,
        0.0
      ],
      [
        0.16649999999999998,
        57.015931606292725,
        {
          "__enum__": "StatusType.SUCCESS"
        },
        1638633544.1715572,
        1638633601.2481112,
        {}
      ]
    ],
    [
      [
        73,
        null,
        0,
        0.0
      ],
      [
        0.19299999999999995,
        45.945780754089355,
        {
          "__enum__": "StatusType.SUCCESS"
        },
        1638633602.6324449,
        1638633648.6545622,
        {}
      ]
    ],
    [
      [
        74,
        null,
        0,
        0.0
      ],
      [
        0.13690000000000002,
        60.88440179824829,
        {
          "__enum__": "StatusType.SUCCESS"
        },
        1638633648.7027347,
        1638633709.6302433,
        {}
      ]
    ],
    [
      [
        75,
        null,
        0,
        0.0
      ],
      [
        0.16649999999999998,
        58.67488718032837,
        {
          "__enum__": "StatusType.SUCCESS"
        },
        1638633710.99624,
        1638633769.7118905,
        {}
      ]
    ],
    [
      [
        76,
        null,
        0,
        0.0
      ],
      [
        0.13839999999999997,
        91.11863851547241,
        {
          "__enum__": "StatusType.SUCCESS"
        },
        1638633770.7938793,
        1638633861.9733455,
        {}
      ]
    ],
    [
      [
        77,
        null,
        0,
        0.0
      ],
      [
        0.17359999999999998,
        54.79348826408386,
        {
          "__enum__": "StatusType.SUCCESS"
        },
        1638633863.370632,
        1638633918.2036912,
        {}
      ]
    ],
    [
      [
        78,
        null,
        0,
        0.0
      ],
      [
        0.13090000000000002,
        54.30125951766968,
        {
          "__enum__": "StatusType.SUCCESS"
        },
        1638633919.6923504,
        1638633974.0436687,
        {}
      ]
    ],
    [
      [
        79,
        null,
        0,
        0.0
      ],
      [
        0.17520000000000002,
        55.51343750953674,
        {
          "__enum__": "StatusType.SUCCESS"
        },
        1638633975.1051886,
        1638634030.6578388,
        {}
      ]
    ],
    [
      [
        80,
        null,
        0,
        0.0
      ],
      [
        0.14390000000000003,
        78.51017808914185,
        {
          "__enum__": "StatusType.SUCCESS"
        },
        1638634032.0280101,
        1638634110.597892,
        {}
      ]
    ],
    [
      [
        81,
        null,
        0,
        0.0
      ],
      [
        0.13019999999999998,
        66.37604999542236,
        {
          "__enum__": "StatusType.SUCCESS"
        },
        1638634110.6452007,
        1638634177.059691,
        {}
      ]
    ],
    [
      [
        82,
        null,
        0,
        0.0
      ],
      [
        0.13049999999999995,
        31.15310311317444,
        {
          "__enum__": "StatusType.SUCCESS"
        },
        1638634178.5595431,
        1638634209.7545104,
        {}
      ]
    ],
    [
      [
        83,
        null,
        0,
        0.0
      ],
      [
        0.17720000000000002,
        54.285563468933105,
        {
          "__enum__": "StatusType.SUCCESS"
        },
        1638634209.803328,
        1638634264.1639862,
        {}
      ]
    ],
    [
      [
        84,
        null,
        0,
        0.0
      ],
      [
        0.13739999999999997,
        77.33109617233276,
        {
          "__enum__": "StatusType.SUCCESS"
        },
        1638634265.2175896,
        1638634342.5878527,
        {}
      ]
    ],
    [
      [
        85,
        null,
        0,
        0.0
      ],
      [
        0.134,
        47.635828256607056,
        {
          "__enum__": "StatusType.SUCCESS"
        },
        1638634342.6371942,
        1638634390.342263,
        {}
      ]
    ],
    [
      [
        86,
        null,
        0,
        0.0
      ],
      [
        0.13260000000000005,
        85.36794972419739,
        {
          "__enum__": "StatusType.SUCCESS"
        },
        1638634391.6943793,
        1638634477.1025279,
        {}
      ]
    ],
    [
      [
        87,
        null,
        0,
        0.0
      ],
      [
        0.15869999999999995,
        57.81325078010559,
        {
          "__enum__": "StatusType.SUCCESS"
        },
        1638634477.1511016,
        1638634535.0076199,
        {}
      ]
    ],
    [
      [
        88,
        null,
        0,
        0.0
      ],
      [
        0.11960000000000004,
        108.34438967704773,
        {
          "__enum__": "StatusType.SUCCESS"
        },
        1638634536.3925946,
        1638634644.782325,
        {}
      ]
    ],
    [
      [
        89,
        null,
        0,
        0.0
      ],
      [
        0.1503,
        65.57844924926758,
        {
          "__enum__": "StatusType.SUCCESS"
        },
        1638634645.8425803,
        1638634711.4616292,
        {}
      ]
    ],
    [
      [
        90,
        null,
        0,
        0.0
      ],
      [
        0.15069999999999995,
        118.22878360748291,
        {
          "__enum__": "StatusType.SUCCESS"
        },
        1638634711.5128322,
        1638634829.7874584,
        {}
      ]
    ],
    [
      [
        91,
        null,
        0,
        0.0
      ],
      [
        0.1291,
        88.23264074325562,
        {
          "__enum__": "StatusType.SUCCESS"
        },
        1638634829.835455,
        1638634918.1428368,
        {}
      ]
    ],
    [
      [
        92,
        null,
        0,
        0.0
      ],
      [
        0.1733,
        72.41919302940369,
        {
          "__enum__": "StatusType.SUCCESS"
        },
        1638634919.5998359,
        1638634992.0817754,
        {}
      ]
    ],
    [
      [
        93,
        null,
        0,
        0.0
      ],
      [
        0.11619999999999997,
        75.8208396434784,
        {
          "__enum__": "StatusType.SUCCESS"
        },
        1638634992.1328597,
        1638635068.017664,
        {}
      ]
    ],
    [
      [
        94,
        null,
        0,
        0.0
      ],
      [
        0.12890000000000001,
        75.04107308387756,
        {
          "__enum__": "StatusType.SUCCESS"
        },
        1638635068.0630105,
        1638635143.180781,
        {}
      ]
    ],
    [
      [
        95,
        null,
        0,
        0.0
      ],
      [
        0.1582,
        46.10256886482239,
        {
          "__enum__": "StatusType.SUCCESS"
        },
        1638635143.2324255,
        1638635189.4242854,
        {}
      ]
    ],
    [
      [
        96,
        null,
        0,
        0.0
      ],
      [
        0.14649999999999996,
        39.47787117958069,
        {
          "__enum__": "StatusType.SUCCESS"
        },
        1638635189.474816,
        1638635229.0092115,
        {}
      ]
    ],
    [
      [
        97,
        null,
        0,
        0.0
      ],
      [
        0.12350000000000005,
        62.126850843429565,
        {
          "__enum__": "StatusType.SUCCESS"
        },
        1638635230.1153827,
        1638635292.3027837,
        {}
      ]
    ],
    [
      [
        98,
        null,
        0,
        0.0
      ],
      [
        0.13429999999999997,
        129.8480794429779,
        {
          "__enum__": "StatusType.SUCCESS"
        },
        1638635293.7128978,
        1638635423.6038096,
        {}
      ]
    ],
    [
      [
        99,
        null,
        0,
        0.0
      ],
      [
        0.16080000000000005,
        67.40814900398254,
        {
          "__enum__": "StatusType.SUCCESS"
        },
        1638635424.998281,
        1638635492.4538913,
        {}
      ]
    ],
    [
      [
        100,
        null,
        0,
        0.0
      ],
      [
        0.11880000000000002,
        42.44172787666321,
        {
          "__enum__": "StatusType.SUCCESS"
        },
        1638635493.8636186,
        1638635536.3629243,
        {}
      ]
    ]
  ],
  "config_origins": {
    "1": "Sobol",
    "2": "Sobol",
    "4": "Sobol",
    "5": "Sobol",
    "6": "Sobol",
    "7": "Sobol",
    "8": "Sobol",
    "9": "Sobol",
    "10": "Sobol",
    "11": "Sobol",
    "12": "Local Search",
    "13": "Sobol",
    "14": "Sobol",
    "15": "Sobol",
    "16": "Sobol",
    "17": "Sobol",
    "18": "Sobol",
    "19": "Sobol",
    "20": "Sobol",
    "21": "Sobol",
    "22": "Sobol",
    "23": "Sobol",
    "24": "Sobol",
    "25": "Sobol",
    "26": "Sobol",
    "27": "Local Search",
    "28": "Local Search",
    "29": "Local Search",
    "30": "Random Search",
    "31": "Random Search",
    "32": "Local Search",
    "33": "Local Search",
    "34": "Local Search",
    "35": "Local Search",
    "36": "Local Search",
    "37": "Local Search",
    "38": "Local Search",
    "39": "Local Search",
    "40": "Local Search",
    "41": "Local Search",
    "42": "Local Search",
    "43": "Random Search",
    "44": "Local Search",
    "45": "Random Search",
    "46": "Local Search",
    "47": "Local Search",
    "48": "Local Search",
    "49": "Random Search",
    "50": "Local Search",
    "51": "Local Search",
    "52": "Random Search",
    "53": "Local Search",
    "54": "Local Search",
    "55": "Local Search",
    "56": "Random Search",
    "57": "Local Search",
    "58": "Local Search",
    "59": "Local Search",
    "60": "Random Search",
    "61": "Random Search",
    "62": "Random Search",
    "63": "Random Search",
    "64": "Local Search",
    "65": "Local Search",
    "66": "Local Search",
    "67": "Random Search",
    "68": "Local Search",
    "69": "Random Search",
    "70": "Local Search",
    "71": "Local Search",
    "72": "Random Search",
    "73": "Random Search",
    "74": "Random Search",
    "75": "Random Search",
    "76": "Random Search",
    "77": "Random Search",
    "78": "Local Search",
    "79": "Random Search",
    "80": "Random Search",
    "81": "Random Search",
    "82": "Local Search",
    "83": "Random Search",
    "84": "Random Search",
    "85": "Random Search",
    "86": "Local Search",
    "87": "Random Search",
    "88": "Random Search",
    "89": "Local Search",
    "90": "Random Search",
    "91": "Random Search",
    "92": "Random Search",
    "93": "Random Search",
    "94": "Random Search",
    "95": "Random Search",
    "96": "Random Search",
    "97": "Random Search",
    "98": "Random Search",
    "99": "Random Search",
    "100": "Local Search"
  },
  "configs": {
    "1": {
      "l2_reg": 0.38930080737918615,
      "lrate": 0.5805931044742465,
      "n_epochs": 124
    },
    "2": {
      "l2_reg": 0.8529080152511597,
      "lrate": 0.08262182772159576,
      "n_epochs": 1978
    },
    "3": {
      "l2_reg": 0.5,
      "lrate": 0.5,
      "n_epochs": 1002
    },
    "4": {
      "l2_reg": 0.717939555644989,
      "lrate": 0.9977498054504395,
      "n_epochs": 832
    },
    "5": {
      "l2_reg": 0.05560271441936493,
      "lrate": 0.49578115344047546,
      "n_epochs": 1192
    },
    "6": {
      "l2_reg": 0.1528269499540329,
      "lrate": 0.8249545097351074,
      "n_epochs": 1636
    },
    "7": {
      "l2_reg": 0.6208297610282898,
      "lrate": 0.3231084644794464,
      "n_epochs": 279
    },
    "8": {
      "l2_reg": 0.9511183500289917,
      "lrate": 0.7226104736328125,
      "n_epochs": 1409
    },
    "9": {
      "l2_reg": 0.29122015833854675,
      "lrate": 0.2245185226202011,
      "n_epochs": 553
    },
    "10": {
      "l2_reg": 0.322373628616333,
      "lrate": 0.8906819224357605,
      "n_epochs": 1360
    },
    "11": {
      "l2_reg": 0.9197698831558228,
      "lrate": 0.39655596017837524,
      "n_epochs": 750
    },
    "12": {
      "l2_reg": 0.5269283652305603,
      "lrate": 0.5617454648017883,
      "n_epochs": 1568
    },
    "13": {
      "l2_reg": 0.24642746150493622,
      "lrate": 0.05580942705273628,
      "n_epochs": 464
    },
    "14": {
      "l2_reg": 0.08669368922710419,
      "lrate": 0.6389495730400085,
      "n_epochs": 908
    },
    "15": {
      "l2_reg": 0.6865324378013611,
      "lrate": 0.1331363469362259,
      "n_epochs": 1015
    },
    "16": {
      "l2_reg": 0.7590690851211548,
      "lrate": 0.7826998829841614,
      "n_epochs": 180
    },
    "17": {
      "l2_reg": 0.4829599857330322,
      "lrate": 0.28845304250717163,
      "n_epochs": 1789
    },
    "18": {
      "l2_reg": 0.4642329514026642,
      "lrate": 0.7503474950790405,
      "n_epochs": 646
    },
    "19": {
      "l2_reg": 0.8091870546340942,
      "lrate": 0.25613105297088623,
      "n_epochs": 1254
    },
    "20": {
      "l2_reg": 0.6355617642402649,
      "lrate": 0.6713248491287231,
      "n_epochs": 435
    },
    "21": {
      "l2_reg": 0.1065247654914856,
      "lrate": 0.16548120975494385,
      "n_epochs": 1543
    },
    "22": {
      "l2_reg": 0.19679862260818481,
      "lrate": 0.52940833568573,
      "n_epochs": 1099
    },
    "23": {
      "l2_reg": 0.5451734662055969,
      "lrate": 0.023441676050424576,
      "n_epochs": 989
    },
    "24": {
      "l2_reg": 0.898478627204895,
      "lrate": 0.9230114221572876,
      "n_epochs": 1823
    },
    "25": {
      "l2_reg": 0.37481167912483215,
      "lrate": 0.4289160966873169,
      "n_epochs": 218
    },
    "26": {
      "l2_reg": 0.2811563014984131,
      "lrate": 0.6902580857276917,
      "n_epochs": 1883
    },
    "27": {
      "l2_reg": 0.5328583441023842,
      "lrate": 0.34366663395236324,
      "n_epochs": 1584
    },
    "28": {
      "l2_reg": 0.531635229030905,
      "lrate": 0.1178461500116273,
      "n_epochs": 1562
    },
    "29": {
      "l2_reg": 0.5217386806012096,
      "lrate": 0.5890518568656948,
      "n_epochs": 1569
    },
    "30": {
      "l2_reg": 0.32897768682371087,
      "lrate": 0.5864981078035306,
      "n_epochs": 1370
    },
    "31": {
      "l2_reg": 0.9312582299465694,
      "lrate": 0.4242808007673212,
      "n_epochs": 352
    },
    "32": {
      "l2_reg": 0.5591967742738811,
      "lrate": 0.42550324858130445,
      "n_epochs": 1568
    },
    "33": {
      "l2_reg": 0.5269283652305603,
      "lrate": 0.5076507954365763,
      "n_epochs": 1591
    },
    "34": {
      "l2_reg": 0.9685282504865684,
      "lrate": 0.5562667509450238,
      "n_epochs": 1567
    },
    "35": {
      "l2_reg": 0.5256138862365416,
      "lrate": 0.5677864167628813,
      "n_epochs": 1568
    },
    "36": {
      "l2_reg": 0.9322928084845513,
      "lrate": 0.5601720789898202,
      "n_epochs": 1568
    },
    "37": {
      "l2_reg": 0.5276060051151912,
      "lrate": 0.5617454648017883,
      "n_epochs": 1568
    },
    "38": {
      "l2_reg": 0.5269283652305603,
      "lrate": 0.5533367976031722,
      "n_epochs": 1568
    },
    "39": {
      "l2_reg": 0.527260006501031,
      "lrate": 0.5616946457045292,
      "n_epochs": 1568
    },
    "40": {
      "l2_reg": 0.5266571150136452,
      "lrate": 0.5617454648017883,
      "n_epochs": 1754
    },
    "41": {
      "l2_reg": 0.5269283652305603,
      "lrate": 0.5624176556737381,
      "n_epochs": 1565
    },
    "42": {
      "l2_reg": 0.5257740321849302,
      "lrate": 0.5617454648017883,
      "n_epochs": 1568
    },
    "43": {
      "l2_reg": 0.6105189990880548,
      "lrate": 0.5229934229676906,
      "n_epochs": 1930
    },
    "44": {
      "l2_reg": 0.5269283652305603,
      "lrate": 0.5617454648017883,
      "n_epochs": 1580
    },
    "45": {
      "l2_reg": 0.03731152346162114,
      "lrate": 0.44690391794750106,
      "n_epochs": 931
    },
    "46": {
      "l2_reg": 0.5269283652305603,
      "lrate": 0.5617454648017883,
      "n_epochs": 1569
    },
    "47": {
      "l2_reg": 0.52676518193585,
      "lrate": 0.5617454648017883,
      "n_epochs": 1568
    },
    "48": {
      "l2_reg": 0.5269283652305603,
      "lrate": 0.5620008091348675,
      "n_epochs": 1567
    },
    "49": {
      "l2_reg": 0.2909410117041956,
      "lrate": 0.42631218076921873,
      "n_epochs": 250
    },
    "50": {
      "l2_reg": 0.5269283652305603,
      "lrate": 0.5569881557287683,
      "n_epochs": 1568
    },
    "51": {
      "l2_reg": 0.5269283652305603,
      "lrate": 0.561799494233355,
      "n_epochs": 1567
    },
    "52": {
      "l2_reg": 0.8899395000024052,
      "lrate": 0.601130649502349,
      "n_epochs": 1142
    },
    "53": {
      "l2_reg": 0.5269283652305603,
      "lrate": 0.5617521986622355,
      "n_epochs": 1568
    },
    "54": {
      "l2_reg": 0.5269842271300031,
      "lrate": 0.5617454648017883,
      "n_epochs": 1567
    },
    "55": {
      "l2_reg": 0.9284939435582501,
      "lrate": 0.07480799523419009,
      "n_epochs": 40
    },
    "56": {
      "l2_reg": 0.9394776881434497,
      "lrate": 0.5598438568733951,
      "n_epochs": 109
    },
    "57": {
      "l2_reg": 0.9455963544643837,
      "lrate": 0.01905177230049377,
      "n_epochs": 8
    },
    "58": {
      "l2_reg": 0.9477328274429566,
      "lrate": 0.11200986120482549,
      "n_epochs": 46
    },
    "59": {
      "l2_reg": 0.5269283652305603,
      "lrate": 0.5617454648017883,
      "n_epochs": 1566
    },
    "60": {
      "l2_reg": 0.3089936395057975,
      "lrate": 0.28461323322284426,
      "n_epochs": 1750
    },
    "61": {
      "l2_reg": 0.8809514230909309,
      "lrate": 0.09672210817357607,
      "n_epochs": 684
    },
    "62": {
      "l2_reg": 0.7080010890213183,
      "lrate": 0.8050219869186324,
      "n_epochs": 568
    },
    "63": {
      "l2_reg": 0.24087422670749004,
      "lrate": 0.34999612042944483,
      "n_epochs": 849
    },
    "64": {
      "l2_reg": 0.935293810040953,
      "lrate": 0.00744614015650601,
      "n_epochs": 24
    },
    "65": {
      "l2_reg": 0.9801449643145659,
      "lrate": 0.019345974694452754,
      "n_epochs": 14
    },
    "66": {
      "l2_reg": 0.5268526022172477,
      "lrate": 0.5617454648017883,
      "n_epochs": 1568
    },
    "67": {
      "l2_reg": 0.46511664436593714,
      "lrate": 0.1718056051987228,
      "n_epochs": 1001
    },
    "68": {
      "l2_reg": 0.5269842271300031,
      "lrate": 0.5617454648017883,
      "n_epochs": 1568
    },
    "69": {
      "l2_reg": 0.3895713396030047,
      "lrate": 0.24333644027147572,
      "n_epochs": 1670
    },
    "70": {
      "l2_reg": 0.5269283652305603,
      "lrate": 0.5610396469521468,
      "n_epochs": 1568
    },
    "71": {
      "l2_reg": 0.5269283652305603,
      "lrate": 0.5617313078313528,
      "n_epochs": 1568
    },
    "72": {
      "l2_reg": 0.13103494460459242,
      "lrate": 0.3030595682879197,
      "n_epochs": 1611
    },
    "73": {
      "l2_reg": 0.4017457992131651,
      "lrate": 0.5117648197119786,
      "n_epochs": 211
    },
    "74": {
      "l2_reg": 0.49879371574223674,
      "lrate": 0.34687479211713723,
      "n_epochs": 1101
    },
    "75": {
      "l2_reg": 0.17083416630631376,
      "lrate": 0.44237536614638917,
      "n_epochs": 407
    },
    "76": {
      "l2_reg": 0.7754514049760909,
      "lrate": 0.6587908246257798,
      "n_epochs": 885
    },
    "77": {
      "l2_reg": 0.5524364632309625,
      "lrate": 0.5367857130179452,
      "n_epochs": 162
    },
    "78": {
      "l2_reg": 0.5269283652305603,
      "lrate": 0.561799494233355,
      "n_epochs": 1568
    },
    "79": {
      "l2_reg": 0.3266126828176048,
      "lrate": 0.8875827003157605,
      "n_epochs": 1374
    },
    "80": {
      "l2_reg": 0.6695808932492974,
      "lrate": 0.42721993928603463,
      "n_epochs": 206
    },
    "81": {
      "l2_reg": 0.7210295140271864,
      "lrate": 0.6471396529028529,
      "n_epochs": 1230
    },
    "82": {
      "l2_reg": 0.9432737298563386,
      "lrate": 0.010604341858144654,
      "n_epochs": 7
    },
    "83": {
      "l2_reg": 0.16262444408302756,
      "lrate": 0.9579110939426391,
      "n_epochs": 867
    },
    "84": {
      "l2_reg": 0.5196409997575183,
      "lrate": 0.7453830502676743,
      "n_epochs": 58
    },
    "85": {
      "l2_reg": 0.012960044108602298,
      "lrate": 0.28497571613513417,
      "n_epochs": 1896
    },
    "86": {
      "l2_reg": 0.5269283652305603,
      "lrate": 0.5617454648017883,
      "n_epochs": 1570
    },
    "87": {
      "l2_reg": 0.6464053817926605,
      "lrate": 0.5910802954777532,
      "n_epochs": 1143
    },
    "88": {
      "l2_reg": 0.9030390544042961,
      "lrate": 0.23171028830861895,
      "n_epochs": 981
    },
    "89": {
      "l2_reg": 0.5269283652305603,
      "lrate": 0.5617454648017883,
      "n_epochs": 1567
    },
    "90": {
      "l2_reg": 0.7498277883315856,
      "lrate": 0.6934913687140332,
      "n_epochs": 1398
    },
    "91": {
      "l2_reg": 0.9782220263963898,
      "lrate": 0.26437482434267845,
      "n_epochs": 784
    },
    "92": {
      "l2_reg": 0.3607219566089881,
      "lrate": 0.9985324737010267,
      "n_epochs": 791
    },
    "93": {
      "l2_reg": 0.2083223454469425,
      "lrate": 0.004413706118984839,
      "n_epochs": 972
    },
    "94": {
      "l2_reg": 0.33112292437128055,
      "lrate": 0.059558980317003796,
      "n_epochs": 640
    },
    "95": {
      "l2_reg": 0.1116358727943616,
      "lrate": 0.26973772673852037,
      "n_epochs": 1723
    },
    "96": {
      "l2_reg": 0.037745110626573264,
      "lrate": 0.21038756027871086,
      "n_epochs": 1724
    },
    "97": {
      "l2_reg": 0.9090367998611453,
      "lrate": 0.15527278914535492,
      "n_epochs": 1274
    },
    "98": {
      "l2_reg": 0.8589714735253257,
      "lrate": 0.2365782961400601,
      "n_epochs": 1667
    },
    "99": {
      "l2_reg": 0.350133026699494,
      "lrate": 0.6228994913971929,
      "n_epochs": 1605
    },
    "100": {
      "l2_reg": 0.9029799675280691,
      "lrate": 0.16240439420299435,
      "n_epochs": 10
    }
  }
}